nexlify_mcp_server/__init__.py
nexlify_mcp_server/main.py
nexlify_mcp_server-0.1.5.dist-info/METADATA
nexlify_mcp_server-0.1.5.dist-info/WHEEL
nexlify_mcp_server-0.1.5.dist-info/entry_points.txt
nexlify_mcp_server-0.1.5.dist-info/RECORD
