Metadata-Version: 2.4
Name: nexlify-mcp-server
Version: 0.1.5
Summary: The Nexlify MCP Server is a lightweight Python package designed to integrate GitHub Copilot with the Nexlify AI system.
Project-URL: Repository, https://github.com/DeepakPant93/nexlify
Project-URL: Documentation, https://github.com/DeepakPant93/nexlify/tree/main/nexlify-mcp-server
Project-URL: Homepage, https://github.com/DeepakPant93/nexlify/blob/main/nexlify-mcp-server/README.md
Author-email: Deepak Pant <mail2deepakpant@gmail.com>
License: MIT License
Requires-Python: >=3.10
Requires-Dist: httpx>=0.28.1
Requires-Dist: mcp[cli]>=1.12.1
